ipeaindices/__init__.py
ipeaindices/indices.py
ipeaindices-0.1.0.dist-info/METADATA
ipeaindices-0.1.0.dist-info/WHEEL
ipeaindices-0.1.0.dist-info/top_level.txt
ipeaindices-0.1.0.dist-info/RECORD
