Metadata-Version: 2.4
Name: ipeaindices
Version: 0.1.0
Summary: Índices do IPEA de forma simples
Author-email: nukhes <nukhes@protonmail.com>
Classifier: License :: OSI Approved :: MIT License
Classifier: Operating System :: OS Independent
Classifier: Intended Audience :: Developers
Classifier: Topic :: Scientific/Engineering :: Information Analysis
Requires-Python: >=3.7
Requires-Dist: ipeadatapy
